{
    "dailyInfo": {
        "Karanan": "07.30-09.00",
        "Sunrise": "06.03",
        "StarDetails": "இன்று அதிகாலை 04.22 வரை மூலம் பின்பு பூராடம்",
        "KaranamDetails": "இன்று அதிகாலை 02.17 வரை பத்திரை பின்பு பிற்பகல் 02.52 வரை பவம் பின்பு பாலவம்",
        "Sulam": "வடக்கு",
        "Parikaram": "பால் ",
        "Namyogam": "இன்று இரவு 11:11 வரை சோபனம் பின்பு அதிகண்டம்",
        "Amirthathiyogam": "இன்று அதிகாலை 04.22 வரை அமிர்தயோகம் பின்பு சித்தயோகம்",
        "Nethiram": "இன்று முழுவதும் ஒரு கண்",
        "Jeevan": "இன்று முழுவதும் அரை வாழ்க்கை",
        "MainDays": "அஷ்டமி(நேற்று பிற்பகல் 01.42 முதல் இன்று பிற்பகல் 02.52 வரை)",
        "SubDays": "சர்வதேச மொழிபெயர்ப்பு தினம், வங்கி அரைவருடக் கணக்கு முடிவு (வங்கி விடுமுறை)",
        "DayDetails": "வளர்பிறை கீழ் நோக்கு நாள்",
        "Pirai": "வளர்பிறை"
    },
    "homedates": {
        "tamilDate": 14,
        "tamilMonth": "புரட்டாசி",
        "tamilYear": "விசுவாசுவ",
        "engMonth": "செப்டம்பர்",
        "engweekDay": "Tuesday",
        "tamilWeekDay": "செவ்வாய்",
        "humanFormat": "செப்டம்பர் 30, 2025"
    },
    "panchangam": {
        "info": "{\"nakshatra\":\"இன்று அதிகாலை 04:22 வரை மூலம் பின்பு பூராடம்\",\"nakshatraTime\":\"\",\"tithi\":\"இன்று பிற்பகல் 02:52 வரை அஷ்டமி பின்பு நவமி\",\"tithiTime\":\"\",\"yogam\":\"சித்த\",\"chandrastram\":\"மிருகசீரிஷம்\"}"
    },
    "panchangamInfo": {
        "tmonth": "புரட்டாசி",
        "tyear": "விசுவாசுவ",
        "tdate": 14,
        "dayAuspicious": null,
        "nneram_mrg": "07.45-08.45",
        "nneram_eve": "04.45-05.45",
        "gneram_mrg": "10.45-11.45",
        "gneram_eve": "07.30-08.30",
        "muhurtham": "N",
        "festival_info": "",
        "thithiimages": "downarrow,valarpirai,,,"
    },
    "chandrastamamRasi": [],
    "chandrastamam": [
        {
            "details": "இன்று அதிகாலை 04.22 வரை கிருத்திகை பின்பு ரோகிணி "
        }
    ],
    "sunmoon": {
        "sun_rise": "06:13 AM",
        "sun_set": "06:09 PM",
        "moon_rise": "01:42 PM",
        "moon_set": "11:51 PM"
    },
    "rasiDaily": [
        {
            "name": "மேஷம்",
            "info": "களிப்பு"
        },
        {
            "name": "ரிஷபம்",
            "info": "வரவு"
        },
        {
            "name": "மிதுனம்",
            "info": "ஆர்வம்"
        },
        {
            "name": "கடகம்",
            "info": "சாந்தம்"
        },
        {
            "name": "சிம்மம்",
            "info": "செலவு"
        },
        {
            "name": "கன்னி ",
            "info": "பாசம்"
        },
        {
            "name": "துலாம்",
            "info": "உறுதி"
        },
        {
            "name": "விருச்சிகம் ",
            "info": "உதவி"
        },
        {
            "name": "தனுசு",
            "info": "கீர்த்தி"
        },
        {
            "name": "மகரம்",
            "info": "கவனம்"
        },
        {
            "name": "கும்பம்",
            "info": "இலாபம்"
        },
        {
            "name": "மீனம்",
            "info": "கவலை"
        }
    ],
    "customData": {
        "ragu_m": "",
        "ragu_e": "03:00 PM - 04:30 PM",
        "yama_m": "09:00 AM - 10:30 AM",
        "yama_e": "",
        "kuligai_m": "",
        "kuligai_e": "12:00 PM - 01:30 PM"
    },
    "inaspiciousDay": {
        "ragu": "3.00 PM-4.30 PM",
        "yama": "9.00 AM-10.30 AM",
        "kuligai": "12.00 PM-1.30 PM"
    },
    "gpanchangamDay": [
        {
            "hora_name": "ரோகம்",
            "hora_time": "06:01 AM - 07:30 AM"
        },
        {
            "hora_name": "லாபம்",
            "hora_time": "07:30 AM - 09:00 AM"
        },
        {
            "hora_name": "தனம்",
            "hora_time": "09:00 AM - 10:29 AM"
        },
        {
            "hora_name": "சுகம்",
            "hora_time": "10:29 AM - 11:58 AM"
        },
        {
            "hora_name": "ரோகம்",
            "hora_time": "11:58 AM - 13:28 PM"
        },
        {
            "hora_name": "உதி",
            "hora_time": "13:28 PM - 14:57 PM"
        },
        {
            "hora_name": "விஷம்",
            "hora_time": "14:57 PM - 16:26 PM"
        },
        {
            "hora_name": "அம்ரிதா",
            "hora_time": "16:26 PM - 17:55 PM"
        }
    ],
    "gpanchangamNight": [
        {
            "hora_name": "ரோகம்",
            "hora_time": "17:55 PM - 19:26 PM"
        },
        {
            "hora_name": "உதி",
            "hora_time": "19:26 PM - 20:57 PM"
        },
        {
            "hora_name": "விஷம்",
            "hora_time": "20:57 PM - 22:28 PM"
        },
        {
            "hora_name": "அம்ரிதா",
            "hora_time": "22:28 PM - 23:58 PM"
        },
        {
            "hora_name": "ரோகம்",
            "hora_time": "23:58 PM - 01:29 AM"
        },
        {
            "hora_name": "லாபம்",
            "hora_time": "01:29 AM - 03:00 AM"
        },
        {
            "hora_name": "தனம்",
            "hora_time": "03:00 AM - 04:30 AM"
        },
        {
            "hora_name": "சுகம்",
            "hora_time": "04:30 AM - 06:01 AM"
        }
    ],
    "horaDay": [
        {
            "hora_name": "செவ்வாய்",
            "hora_time": "06:01 AM - 07:01 AM"
        },
        {
            "hora_name": "சூரியன்",
            "hora_time": "07:01 AM - 08:00 AM"
        },
        {
            "hora_name": "சுக்ரன்",
            "hora_time": "08:00 AM - 09:00 AM"
        },
        {
            "hora_name": "புதன்",
            "hora_time": "09:00 AM - 09:59 AM"
        },
        {
            "hora_name": "சந்திரன்",
            "hora_time": "09:59 AM - 10:59 AM"
        },
        {
            "hora_name": "சனி",
            "hora_time": "10:59 AM - 11:58 AM"
        },
        {
            "hora_name": "வியாழன்",
            "hora_time": "11:58 AM - 12:58 PM"
        },
        {
            "hora_name": "செவ்வாய்",
            "hora_time": "12:58 PM - 13:57 PM"
        },
        {
            "hora_name": "சூரியன்",
            "hora_time": "13:57 PM - 14:57 PM"
        },
        {
            "hora_name": "சுக்ரன்",
            "hora_time": "14:57 PM - 15:56 PM"
        },
        {
            "hora_name": "புதன்",
            "hora_time": "15:56 PM - 16:56 PM"
        },
        {
            "hora_name": "சந்திரன்",
            "hora_time": "16:56 PM - 17:55 PM"
        }
    ],
    "horaNight": [
        {
            "hora_name": "சனி",
            "hora_time": "17:55 PM - 18:56 PM"
        },
        {
            "hora_name": "வியாழன்",
            "hora_time": "18:56 PM - 19:56 PM"
        },
        {
            "hora_name": "செவ்வாய்",
            "hora_time": "19:56 PM - 20:57 PM"
        },
        {
            "hora_name": "சூரியன்",
            "hora_time": "20:57 PM - 21:57 PM"
        },
        {
            "hora_name": "சுக்ரன்",
            "hora_time": "21:57 PM - 22:58 PM"
        },
        {
            "hora_name": "புதன்",
            "hora_time": "22:58 PM - 23:58 PM"
        },
        {
            "hora_name": "சந்திரன்",
            "hora_time": "23:58 PM - 00:59 AM"
        },
        {
            "hora_name": "சனி",
            "hora_time": "00:59 AM - 01:59 AM"
        },
        {
            "hora_name": "வியாழன்",
            "hora_time": "01:59 AM - 03:00 AM"
        },
        {
            "hora_name": "செவ்வாய்",
            "hora_time": "03:00 AM - 04:00 AM"
        },
        {
            "hora_name": "சூரியன்",
            "hora_time": "04:00 AM - 05:01 AM"
        },
        {
            "hora_name": "சுக்ரன்",
            "hora_time": "05:01 AM - 06:01 AM"
        }
    ],
    "panchangamDetail": {
        "Panchangam": [
            {
                "name": "திதி",
                "value": "த்ரயோதஶீ - 19:09:32 வரை"
            },
            {
                "name": "நக்ஷத்திரம்",
                "value": "மகம் - 06:19:37 வரை"
            },
            {
                "name": "கரணம்",
                "value": "வணிஜ - 19:09:32 வரை"
            },
            {
                "name": "பக்ஷம்",
                "value": "தேய்பிறை"
            },
            {
                "name": "யோகம்",
                "value": "ஶுப - 25:17:12 வரை"
            },
            {
                "name": "கிழமை",
                "value": "திங்கள் கிழமை"
            }
        ],
        "MangalaNeram": [
            {
                "name": "அபிஜித்",
                "value": "11:46:55 12:34:30, இருந்து"
            }
        ],
        "Dishai": [
            {
                "name": "திசை சூலம்",
                "value": "கிழக்கு"
            }
        ],
        "Moon": [
            {
                "name": "தர பல",
                "value": "அஸ்வினி, பரணி, கார்த்திகை, ம்ருகஷீர்ஷம், புனர்பூசம், ஆயில்யம், மகம், பூரம், உத்திரம், சித்திரை, விசாகம், கேட்டை, மூலம், பூராடம், உத்திராடம், அவிட்டம், பூரட்டாதி, ரேவதி"
            },
            {
                "name": "சந்திர பல",
                "value": "மிதுந, ஸிம்ஹ, துலா, வ்ருச்சிகம், கும்ப, மீனம்"
            }
        ]
    }
}